oneNeuron_pypi/__init__.py
oneNeuron_pypi/perceptron.py
oneNeuron_pypi_DhyeySherasia-0.0.2.dist-info/LICENSE
oneNeuron_pypi_DhyeySherasia-0.0.2.dist-info/METADATA
oneNeuron_pypi_DhyeySherasia-0.0.2.dist-info/WHEEL
oneNeuron_pypi_DhyeySherasia-0.0.2.dist-info/top_level.txt
oneNeuron_pypi_DhyeySherasia-0.0.2.dist-info/RECORD
