Metadata-Version: 2.1
Name: oneNeuron-pypi-DhyeySherasia
Version: 0.0.2
Summary: An implementation of Perceptron in Python
Home-page: https://github.com/DhyeySherasia/oneNeuron_pypi
Author: DhyeySherasia
Author-email: dhyeysherasia2002@gmail.com
License: UNKNOWN
Project-URL: Bug Tracker, https://github.com/DhyeySherasia/oneNeuron_pypi/issues
Platform: UNKNOWN
Classifier: Programming Language :: Python :: 3
Classifier: License :: OSI Approved :: MIT License
Classifier: Operating System :: OS Independent
Requires-Python: >=3.7
License-File: LICENSE
Requires-Dist: numpy
